Metadata-Version: 1.2
Name: doodle-dashboard
Version: 0.0.20
Summary: Extensible dashboard designed to display data from multiple sources.
Home-page: https://github.com/SketchingDev/Doodle-Dashboard
License: MIT
Platform: UNKNOWN
Classifier: Development Status :: 3 - Alpha
Classifier: Programming Language :: Python :: 3.4
Requires-Python: >=3.4
